cluesbysam_solver/__init__.py
cluesbysam_solver-0.2.0.dist-info/WHEEL
cluesbysam_solver-0.2.0.dist-info/METADATA
cluesbysam_solver-0.2.0.dist-info/RECORD
