Metadata-Version: 2.4
Name: cluesbysam-solver
Version: 0.2.0
Summary: Wrapper around the Z3 SMT Solver to assist in solving CluesBySam puzzles.
Author: Joost Rijneveld
Author-email: Joost Rijneveld <joost@joostrijneveld.nl>
License-Expression: MIT
Requires-Dist: z3-solver>=4.15.4.0
Requires-Python: >=3.13
Project-URL: Repository, https://github.com/joostrijneveld/cluesbysam-solver.git
